LICENCE
MANIFEST.in
README.mkd
requirements.txt
setup.py
tergraw/__init__.py
tergraw/__main__.py
tergraw/constant.py
tergraw/graphutils.py
tergraw/info.py
tergraw/tergraw.py
tergraw/view.py
tergraw.egg-info/PKG-INFO
tergraw.egg-info/SOURCES.txt
tergraw.egg-info/dependency_links.txt
tergraw.egg-info/requires.txt
tergraw.egg-info/top_level.txt