Metadata-Version: 1.1
Name: tergraw
Version: 0.3.1
Summary: Draw graphs in terminal
Home-page: https://github.com/Aluriak/tergraw
Author: lucas
Author-email: lucas.bourneuf@laposte.net
License: UNKNOWN
Keywords: graph terminal draw
Platform: UNKNOWN
Classifier: License :: OSI Approved :: GNU General Public License (GPL)
Classifier: Natural Language :: English
Classifier: Operating System :: Unix
Classifier: Programming Language :: Python :: 3
Classifier: Topic :: Software Development :: Libraries :: Python Modules
